[
    {
        "id" : 1,
        "project" : "Global Travel Website",
        "image": "./assets/images/global-travel-website.jpg",
        "description": "This a travel app that allows people to book tickets and view destinations.",
        "deployed": "https://dkt15.github.io/globe-travel-website/",
        "repo": "https://github.com/DKT15/globe-travel-website"
    },
    {
        "id" : 2,
        "project" : "Daily Planner App",
        "image": "./assets/images/daily-planner-app.png",
        "description": "This a travel app that allows people to book tickets and view destinations.",
        "deployed": "https://dkt15.github.io/daily-planner-app/",
        "repo": "https://github.com/DKT15/daily-planner-app"
    },
    {
        "id" : 3,
        "project" : "UK Library Book Store",
        "image": "./assets/images/uk-library-bookstore.png",
        "description": "This a travel app that allows people to book tickets and view destinations.",
        "deployed": "https://dkt15.github.io/UK-Library-book-store/",
        "repo": "https://github.com/DKT15/UK-Library-book-store"
    },
    {
        "id" : 4,
        "project" : "Pasword Generator",
        "image": "./assets/images/password-generator.jpg",
        "description": "This a travel app that allows people to book tickets and view destinations.",
        "deployed": "https://dkt15.github.io/password-generator-challenge/",
        "repo": "https://github.com/DKT15/password-generator-challenge"
    },
    {
        "id" : 5,
        "project" : "My first portfolio website",
        "image": "./assets/images/first-portfolio.jpg",
        "description": "This a travel app that allows people to book tickets and view destinations.",
        "deployed": "https://dkt15.github.io/Dante-E-portfolio/",
        "repo": "https://github.com/DKT15/Dante-E-portfolio"
    },
    {
        "id" : 6,
        "project" : "Console Finances",
        "image": "./assets/images/console-finances.png",
        "description": "This a travel app that allows people to book tickets and view destinations.",
        "deployed": "https://dkt15.github.io/DKT-console-finances/",
        "repo": "https://github.com/DKT15/DKT-console-finances"
    }
]